tf_bind_transformer/__init__.py
tf_bind_transformer/attention.py
tf_bind_transformer/cache_utils.py
tf_bind_transformer/context_utils.py
tf_bind_transformer/data.py
tf_bind_transformer/data_bigwig.py
tf_bind_transformer/gene_utils.py
tf_bind_transformer/optimizer.py
tf_bind_transformer/protein_utils.py
tf_bind_transformer/tf_bind_transformer.py
tf_bind_transformer/training_utils.py
tf_bind_transformer/training_utils_bigwig.py
tf_bind_transformer-0.0.118.dist-info/LICENSE
tf_bind_transformer-0.0.118.dist-info/METADATA
tf_bind_transformer-0.0.118.dist-info/WHEEL
tf_bind_transformer-0.0.118.dist-info/top_level.txt
tf_bind_transformer-0.0.118.dist-info/RECORD
