Metadata-Version: 2.1
Name: tf-bind-transformer
Version: 0.0.118
Summary: Transformer for Transcription Factor Binding
Home-page: https://github.com/lucidrains/tf-bind-transformer
Author: Phil Wang
Author-email: lucidrains@gmail.com
License: MIT
Keywords: artificial intelligence,deep learning,attention mechanism,transformers,transcription factors,gene expression
Classifier: Development Status :: 4 - Beta
Classifier: Intended Audience :: Developers
Classifier: Topic :: Scientific/Engineering :: Artificial Intelligence
Classifier: License :: OSI Approved :: MIT License
Classifier: Programming Language :: Python :: 3.6
License-File: LICENSE
Requires-Dist: bidirectional-cross-attention
Requires-Dist: biopython
Requires-Dist: click
Requires-Dist: einops (>=0.3)
Requires-Dist: enformer-pytorch (>=0.5)
Requires-Dist: fair-esm
Requires-Dist: logavgexp-pytorch
Requires-Dist: polars
Requires-Dist: python-dotenv
Requires-Dist: sentencepiece
Requires-Dist: torch (>=1.6)
Requires-Dist: transformers (>=4.0)
Requires-Dist: tqdm
